{"packageName":"com.infa.odin.models.Script","packageDescription":"Script model","packageLabel":"Script","deprecated":false,"subsystem":false,"cdc":true,"classes":[{"name":"Calculation","label":"Calculation","description":"","isFirstClass":true,"superClasses":["core.Calculation","core.IClass"],"deprecated":false,"isAbstract":false,"cdc":true,"indexType":"FULL","appendOnly":false,"extensions":[],"softDeleted":false,"system":false},{"name":"Folder","label":"Folder","description":"","isFirstClass":true,"superClasses":["core.Container","core.IClass"],"deprecated":false,"isAbstract":false,"cdc":true,"indexType":"FULL","appendOnly":false,"extensions":[],"softDeleted":false,"system":false},{"name":"Script","label":"Script","description":"","isFirstClass":true,"superClasses":["core.DataProcess","core.IClass"],"deprecated":false,"isAbstract":false,"cdc":true,"indexType":"FULL","appendOnly":false,"extensions":[],"softDeleted":false,"system":false},{"name":"Statement","label":"Statement","description":"","isFirstClass":true,"superClasses":["core.DataProcess","core.IClass"],"deprecated":false,"isAbstract":false,"cdc":true,"indexType":"FULL","appendOnly":false,"extensions":[],"softDeleted":false,"system":false}],"requiredPackages":["core"],"associations":[{"name":"FolderToFolder","label":"Folder to Folder","fromClass":"com.infa.odin.models.Script.Folder","toClass":"com.infa.odin.models.Script.Folder","fromLabel":"Folder","toLabel":"Folder","associationKinds":["core.ParentChild","core.IAssociation"],"deprecated":false,"cdc":true,"unidirectional":false,"aggregate":false,"description":"","customizable":false,"custom":false,"deleted":false},{"name":"FolderToScript","label":"Folder to Script","fromClass":"com.infa.odin.models.Script.Folder","toClass":"com.infa.odin.models.Script.Script","fromLabel":"Folder","toLabel":"Script","associationKinds":["core.ParentChild","core.IAssociation"],"deprecated":false,"cdc":true,"unidirectional":false,"aggregate":false,"description":"","customizable":false,"custom":false,"deleted":false}],"attributes":[{"name":"callStackTrace","label":"Call stack trace","dataType":"core.String","description":"","multivalued":false,"deprecated":false,"derived":false,"data":false,"defaultValues":[],"custom":false,"isSystem":false,"embedded":false,"reference":"","referencedAttributes":[],"searchConfiguration":{"suggestable":false,"aggregatable":false,"sortable":false,"attributeType":"VIEWABLE"},"projectionExpressions":[],"deleted":false,"customizations":["NONE"]},{"name":"errorMessage","label":"Error message","dataType":"core.String","description":"","multivalued":false,"deprecated":false,"derived":false,"data":false,"defaultValues":[],"custom":false,"isSystem":false,"embedded":false,"reference":"","referencedAttributes":[],"searchConfiguration":{"suggestable":false,"aggregatable":false,"sortable":false,"attributeType":"VIEWABLE"},"projectionExpressions":[],"deleted":false,"customizations":["NONE"]},{"name":"sourceCode","label":"Source code","dataType":"core.String","description":"","multivalued":false,"deprecated":false,"derived":false,"data":false,"defaultValues":[],"custom":false,"isSystem":false,"embedded":false,"reference":"","referencedAttributes":[],"searchConfiguration":{"suggestable":false,"aggregatable":false,"sortable":false,"attributeType":"VIEWABLE"},"projectionExpressions":[],"deleted":false,"customizations":["NONE"]},{"name":"sourceStatementText","label":"Source statement text","dataType":"core.String","description":"","multivalued":false,"deprecated":false,"derived":false,"data":false,"defaultValues":[],"custom":false,"isSystem":false,"embedded":false,"reference":"","referencedAttributes":[],"searchConfiguration":{"suggestable":false,"aggregatable":false,"sortable":false,"attributeType":"VIEWABLE"},"projectionExpressions":[],"deleted":false,"customizations":["NONE"]},{"name":"statementCommentText","label":"Statement comment text","dataType":"core.String","description":"","multivalued":false,"deprecated":false,"derived":false,"data":false,"defaultValues":[],"custom":false,"isSystem":false,"embedded":false,"reference":"","referencedAttributes":[],"searchConfiguration":{"suggestable":false,"aggregatable":false,"sortable":false,"attributeType":"VIEWABLE"},"projectionExpressions":[],"deleted":false,"customizations":["NONE"]}],"classAttributes":[{"className":"com.infa.odin.models.Script.Script","attributeName":"com.infa.odin.models.Script.sourceCode","isRequired":false,"isCuratable":false,"deprecated":false,"followers":[],"isHidden":false,"cdc":true,"custom":false,"gatherStats":false,"materialized":false,"conditions":[],"deleted":false},{"className":"com.infa.odin.models.Script.Statement","attributeName":"com.infa.odin.models.Script.callStackTrace","isRequired":false,"isCuratable":false,"deprecated":false,"followers":[],"isHidden":false,"cdc":true,"custom":false,"gatherStats":false,"materialized":false,"conditions":[],"deleted":false},{"className":"com.infa.odin.models.Script.Statement","attributeName":"com.infa.odin.models.Script.errorMessage","isRequired":false,"isCuratable":false,"deprecated":false,"followers":[],"isHidden":false,"cdc":true,"custom":false,"gatherStats":false,"materialized":false,"conditions":[],"deleted":false},{"className":"com.infa.odin.models.Script.Statement","attributeName":"com.infa.odin.models.Script.sourceStatementText","isRequired":false,"isCuratable":false,"deprecated":false,"followers":[],"isHidden":false,"cdc":true,"custom":false,"gatherStats":false,"materialized":false,"conditions":[],"deleted":false},{"className":"com.infa.odin.models.Script.Statement","attributeName":"com.infa.odin.models.Script.statementCommentText","isRequired":false,"isCuratable":false,"deprecated":false,"followers":[],"isHidden":false,"cdc":true,"custom":false,"gatherStats":false,"materialized":false,"conditions":[],"deleted":false}],"dataTypes":[],"associationKinds":[],"associationAttributes":[],"references":[],"associationKindAttributes":[],"classUserKeys":[],"classPartitionKeys":[],"associationPartitionKeys":[],"namespaces":[],"packageNamespaces":["default"],"identity":"","version":4,"modifiedBy":""}